HeST/Amherst_Example_Detector.py
HeST/Detection.py
HeST/HeST_Core.py
HeST/LBNL_Example_Detector.py
HeST/LCE_map_amherstExample_41x41x30_noReflections.npy
HeST/LCE_map_lbnlExample_51x51x30_noReflections.npy
HeST/QP_map_amherstExample_41x41x30_noReflections.npy
HeST/QP_map_lbnlExample_51x51x30_noReflections.npy
HeST/WIMP_Generation.py
HeST/__init__.py
HeST-0.2.0.dist-info/LICENSE
HeST-0.2.0.dist-info/METADATA
HeST-0.2.0.dist-info/WHEEL
HeST-0.2.0.dist-info/top_level.txt
HeST-0.2.0.dist-info/RECORD
