Metadata-Version: 2.1
Name: HeST
Version: 0.2.0
License-File: LICENSE
Requires-Dist: numpy
Requires-Dist: scipy
Requires-Dist: detprocess
Requires-Dist: re
